{
  "meta": {
    "run_id": "42549e25-24c5-4486-b800-a7d8f465c253"
  },
  "num_chunks": 10,
  "chunks": [
    {
      "index": 0,
      "text": "e6 99 HAs aoa Q1Ay 7 eau sone! JS ===PAGE_BREAK=== eayqomgad FP SOK?! 1S, AIBOIAL O14 SIOlFt RSM aA SotH SE Olotot7| Sorte! 1S, OBA S + QSLICt SHAl Sot], OSA] OF 2 St = QISLICt ===PAGE_BREAK=== SO?! lS, ALSOHAl 1! SIDIAk RSM ===PAGE_BREAK=== SoHAMUTS 71 Atel HO SES] No.I Ale! 7122] kZI01 SICH ayexon Ls] BIO] SOHO! TS REY BAMHIA 2S Aa& SOS BW Ale sa 917] & SOHO! TBO] SI ; 7B%7t Sone! Az 7 OS SSAC! WB 73% og, HSO| A 2S MBIAA BIT 4 Al Bl SS SSS 4NH2t9| AS SAS AA Sore! 23S0I ASOe AIO QIAO EI am e “AIS SHOAl Hel, AA Se, SUBS S ar ~< —w > Reade sey, acta BE HIP} ap MES @c® fA] GEA 26918 / S0ne! PEA IIS (2.04%) “2018.12 I= ===PAGE_BREAK=== SoHATS 7/12 Atel Sone! SSO] StAlS SKOHCt AtOHo! TS ASpO} SH Ponusuned ChOFSE SOHO! 1S CHAd OFA SSE aoel= Eg SHOWS Sit 44813123 (Barrier Free) Er=~ C1 0F OHO OFLt’? “Qo AA OS AIH 2} AoIatOH Ee _ AMEPAIDI ALES AIZS AIDY ‘AAIAIA} Gt 4 ont = ipenanae _ AIS [Hop S WAS ones H|ZHOHOIaI} ZtOHO1O] [XS O|n|7} Sick BIC ZPUSS AA TSE! BONS 2 ASIA A7|-AIAt BEI JIAICIAHC! HOPI BSS ary 150i BBE SS ofeI Ogy - SOHO! 31 2HO] SIZOWAY Hah B= SHB AS z!03 aA] 2=At 100,016S / tone! SEA 1 SB6S (1.54%) *2UIB eS JIZ= ===PAGE_BREAK=== SHAS] SIO] 7a ESG SBS Meoo) Sous’"
    },
    {
      "index": 1,
      "text": "|ESG 83a | Ars AEA aed | 66 PISO] ASIA MOIS Vast + ge “oc TH AS Bisel SHO] Vsto= “SONS! 1S\" Ol] CHS SHA StCH | ABQ] Soe! WS Old | AISIO] AbSIzA AA7HSSS ZSOHOM Se nos Sete is342 AHO! -O|&H aE zs zip al ol ===PAGE_BREAK=== SHAS] SIO] CSS ste] MEO Boas” Crs tel | EEA MS (ea | S S IOOCH ISO} ChorAt Bay AAs Clorst DRAHSO| AS SEY HHS! 42%2l AS “Crest +$ Se” Solid Sols BS AAI OlS] | Cist ===PAGE_BREAK=== HS =e = SA Solz. S, AAAHSt9l BA APS] AA] O] YI} BA] ABS APSO A 7H 29}5]7]4} wH AR] A}O] BYRT} SrA] OB AYEIy. %, AALS 7PF AHP Alo] Ye ASAA] Bz]S AHS} spe Suh 7} 3129 AHS 8H O|CH. a] 43) 2}0]7]] 214.2] 0}50] & a, At EVES O8]a] GIRS Woe Qyse A gle _# E4, ¥Y2|S(A Theory of Justice) $ ot AH2I0| Hora A\\B2I stele AHOHO! TSO} As| +35 let Asl+Se B>=7t Lt ZO! OFS OHOF St AIAl= SSaQ| Hel ===PAGE_BREAK=== HS =e ‘71S! O] BSat 29] BS SAIALS| PAS! DES OMSET SHES] S17] QPSHAE ‘2(S/ QO] BSA SHA] ‘AA’ QO] BSO| 2t01{ANOF St 7|s|O] BS X>0] Wi = a= OS ===PAGE_BREAK=== Sone! 1S, CE ABE USA otal RSVP Sot SH SSota RE ABS AMBSTHStwWAlaS Sl “2018 eS AZ ZIOHOI 327} “2020.94 7iz - ONDE TP ene aan P..=+ ZOHO! EEA 172 » ’ . 703 9 SA DSA Fm _ ® 3.7543 €& SS ame AJA] DEA 5503 Kinyo’ AL oA! [=| At ya 7tO Soh] Akx"
    },
    {
      "index": 2,
      "text": "oS ‘SOHP’ AH SAI WAPI |HEY Ala o 782i 219] sets 3% ZSOFAHOHOI & Bas re Orr MES of CRASH SE as Aa heoe Jf AAA! P37 |at Aw ZIBILH IOHCIOIAIHA TSS AISHSHE S BLOW! AIS 7H WOR eziSRISeCE) SOHO! ASO] SI |Z2i PSs > Ve OH Oral 1H Bt0|| DSS 3a OSH EES AIBIOH SIAC ZO SIASOHOI TSS} SISO}, 2 ASE Az SS -B- OS HOWMMSES Oot ASH AAO CUrarSAV SIMS Alsou oO AA ws, 01 S49 AlelSsOe _ ad aie us Alc AS PUSSl AAASSS ate Cle ME ===PAGE_BREAK=== an Qo SE OloHot7| ===PAGE_BREAK=== Zt0H BO] WEE S17) as0H, MICH SOOk Ol S VSLICt Sone lojet Chefst FHSS Cloy, CEH AST SSO AZ|] AOS AS SHAE S729] NAIA, SAA, Al, data Ass 7H ABS BStelct. SHSA SoHMVSSA 3! Aes UNS one! Wels et AIA // ff | > wa SoHE AAA - SUA SOK Lloro} SSOHSOfEt AIA] = SASSO] SOW OUSok Skat S! ApS] BHO 7 (Z0ll BA A] i ROM set Aes BSH At sso AS BSH Ar ===PAGE_BREAK=== Sons SE ts Sols SE SHO! Sstol! VSLICt ASI2] BH Oj BY SJ SAIS AAOIAl ON SANE SHEA! FHEl9] aHe! BGHS A VSL? oY SVS AsO OS BA EAI SoS F QSL A|LIA] Sol, SAS ASS JAAS OEE OASO! RSL oS ANBSO] SAT store SHS A A2tAro] SH HHO] HAS ApetsSa} OJAFAS OK GI] HALO] VSL? oA Alo] HAZEL SOH7} HA SISHSLSILT OES: BIS OleIaI SILIQ? oS BARA SALE HAP SAO! JAS OlSotEl WASS SSAl7ILtQ\"e"
    },
    {
      "index": 3,
      "text": "AHL] SAAT At SiO] SAS / SEO] BEY OH2s4HS WFBILICE ===PAGE_BREAK=== ZOHSSIO| O18H SeAlLict= 15719] SuSSs BAC ao! RSUC  Sano 2 Son i Son SsOHe! QI HA XiMOH «= SZESION «(i AISERION «SBT ISTO Lieto lofty «==sCAattON REIN y ols  y UWS ss AI2HE0H «= SEEASOH «= PFO MI IESSFON OPA ZO! OFS O15 OBI} Sila Zou Bret ZI0H AAl Zt0H X=AZ20H A204 AHMISZIOH bs a ===PAGE_BREAK=== SOURS Oot SE SHH 210171! SSC SP 2lLtct Sorte! Ol-| BIE Sal ee ese ter acne ees) 45.1« AAW] Ol-ACHH] Atoyo! O1m 2 645,0002) 51% 15.6% 95. 9.4 AIAMSOH =9SASOH SAISON ISH 22|Ltzt S0We! SASS 5% LHS] Merwe ea taeers een crepes OECD 27} 24.5% TAS St = 5% Lygl eu ===PAGE_BREAK=== SOKSIOi] CHSt AlApatt EHS CHSHHMIOIAL SELES SON2!9] SS o Ade Sa fi AIO CHO] HALT W[AtstS Ae HEI] ACIS! LHS Hoy N2HS0| DSS Edt AG SA= SOHE SHOT JBst Zool] SSet g72027 oS SA SONS Siok SAE ORS! OSCE O|OFF|SS Son, 4st AFSIOIA] QIZIOlF| SONS HOS MAS ORO| SOS 7A! AMQA SAE atts SS BOHOLS fs BYSET rr 23| AfS] 237} HERIOIOF SICH= auzte OFStAlz! [=0| 22st EM eiAAlz ===PAGE_BREAK=== SFOHSI0{] CHSt Aj2tat EX Sols SE ASHE SBS] Of! meastO| ZQSLict ~~ BOHOL Zt CHSHE BAAS LHS ZAHSK= 210] OFLILICH BE A[2}aotel= BE Azole AALS etc}? 018 ASSL? ”-—c—cUmUc™! es ‘e"
    },
    {
      "index": 4,
      "text": "ESS BME AA SHB] OA Solo} @ — ms ===PAGE_BREAK=== A Sones, OSA S = VSL ===PAGE_BREAK=== SoHAMVSS| SA, ALA Lis SeiLicrol Soe! SSH, SO?! US LISS SOK?! ISVS CES DSOE NSE OWS AAA CEA Se 9] CKLWA] IZA HSol= SHIGA ASAOS SoH OE Al “OF DSHS : SAP ASAICHA, SA DEA SOS OltsS DSO WE AB Sue! 1S Sea St 1003 ole 7a ZOHO OSE c o © St REIS ACH CHSt Sts Ale wr SEARO] Wess Os set MA ===PAGE_BREAK=== SOHNTSO| HAY, AIA LHS ZSOHOIO] TIA SI ALOU SHE O| HE Sonelo| A SH SE AAHSS Sordi x 0] TWL2AB4| al ex as One! io = zl Se OIFIC}L AHSIS SEA io) === ZHOHOIO} ImzA | ol a AlO1TH = 2S Wore AS SACe sic} @ Zone! Saas A Saraol at qo © wore! AAe nee wal ws sone! 1S5%! 3! =o) Har @ ore! #za-Lea we @) Bone! xtor se @ 7c), BS, JIEf Eo] ArSIzY 4HE! O14 ===PAGE_BREAK=== ZOHNTSO| HAY, AIA LHS Soe! DSIUSAME Set SOP! LSE9) Ast SoHo! IS VSeo| Ast OFASAAA SoHe! WSAz 20214 2 7|e aa5/7 aA Wass 7lzt | 3 Ay 3.6% 3.6% 3.8% rag Pe eUee e0cd e024 OFS ABA Soe! WSs 3.1% | BZA | So7lt Soe! WSs 3,./Bx glo 3s S.le S.le EEE HE rag eUee eUcd e024 ===PAGE_BREAK=== ZOHNTSO| HAY, IEA LHS STL 22 > ME SHS SUC SOHSI-FOt AAO! 9| SABSSEW lat | 2022 ater] | m@ Z01ol> BAAS 69.2% AiW|StSAhp +S 12= AHS Lot aeo= =O rc"
    },
    {
      "index": 5,
      "text": "SA : SHSAOHCTSSCH, \"LOLLY AMI] SOHSMISESAEWBAL, ===PAGE_BREAK=== MAS Ale Al Sote! TSS Filet, SAS OSet ASA SS make) VS? Aen 9 O “x2 SOI MsSAst Se 2! USS Set Bol olFZIOHA) B! 215 SOR AGE A BI AIA = 3 a SSAA alg MIA HIB AKA AIHA USS AHA Ars MBIA \"des CHASE) DAICHSH/SSAOHO! CME + ZHOITO|X| $I Aoyol 71S BsrHAAel 127/219! oViLlo onwTeo __ __ L Lo, (4 SSDSAlSIMHIA) HSS) AWcs/tSeH, Soen HAZSH|| -AHIA NSS Hse) DSetelyls Ale! -1S2tyS ze oOlapet TSAtay= ZH MOANA) BoHIScs AAS + 1SH9|7| BA + ZLOHO! QIAI7HAS FIO! O1AIHA Ie SNE) BENS Az Ales as ===PAGE_BREAK=== MBAS Ale Al SHS ASF OF dls SS s MUL? 1Sdris ASD 244 71) Soe! TSseAs as ea | as oa i q5orel | soot! igs Sous BOI St=IZtOHO! F185 | ore. | ore igst At APIA nee S0es ‘TtwssAs SOHSI9] HHS S&S Sion 0 SAGES?! 52! OlS SOP! OB At @ Sole! SEAS At asot0} Al2s VSS Az 7S Old 1S Salat SS ===PAGE_BREAK=== MBS Ale! ALE Sols LSorH 1M dS 2S se MUL? Alone! BH=Ae12! a=] Al = “oun SA BEA S sone! Soe! PaEAS ssoone! SOW?! PAS oO Atk loot ole 30% oat 2Suls OlS ASIAS BHEMNAS ASIAtS| SOHAIL AS DSA] SOP ISo|Solelor Heo Sa 7H : wits DOSCO 66 ae ey ' Oe PARRA ~~ LH Iss ALSIATSS °° een pnts rg 7 ia 4, = SOHIRSALS BRAASHA “O|OIAl BA: BADRHA ===PAGE_BREAK=== MBAS Ale Al"
    },
    {
      "index": 6,
      "text": "Sols AZo OF WHS SS s RUL? CHAN! As BASS Ala SSSI] IA, BOHOl0| AAS SSAOH AISA AIMS SHEE AIP AGS! A WEE FI Soe! CEA a SHA SSel, SOS DSol QOL} VSode= AAS, 4el Olot #219] Sone! AA BSHA Sst7|7| SSsaone! 12 BAZ, = 40Al25 OL Aes PASS|P| ===PAGE_BREAK=== S174] 16H, OlZI7I SHE! BtSt + VISLIC} SS ME ===PAGE_BREAK=== Olwat FOHe! ols =+Lt 2) BO] SST ok 24 Ge ale zoe’ 2ett JAS OPI ASs S72 dels MIC CHethl=; S12] AOA SoHo! MAA FHS 19] SAF 7A]S 71710] YBS AVY AelS 7H, BOHM AAT ApS] PASO w Wo] YL abe sop7}o} APIO] 52S 7YUS}O}] APYS-ES te 2s}O] oF Sep A7}} APL Yat BAJA] Boye] Be] ao] alo] qe} FHM] IAL BSA VA A}9] 40} } WES o}Zo} CO} LOPHE APD]S THS7] 91 ¥t fT} AS ZYS}OoF Ge}, _ OH ASMA ===PAGE_BREAK=== Aa Sorel Ola + Lt O12) Ol SS LiCiOk ot= 2! UN Sore! Belset Yeo! - f AOE BAAOS ASE 7HNG, id E293 Ald APES} 25°] GE ARES SS orl Ars) SHMopal SIA Os Foote AS A/oHob= EE B BAA BY 79] YSAGCSBE) 7/AMAHE AS WV. SrOHON AIBIOR A OFS RIZHHIS 4 Olt A SA] Os _ UNZOHe! Bel sor AE(e)ae otion LL. ae SPH Ale AAA ApS|2I2I Bi24, AHAO| Chat BST} MAE S54, USA, HAA ABI Bay ABI Bel ————tlti Cs _§ £e~yx_we HOH, AHA, AléHlO] CHAS AIBIOBMO| We] 1 2A : ZISIA\\(2008) LINSOHOIBAAFAE OHIO) A/BIAY Ba ===PAGE_BREAK=== So?! SAS a2"
    },
    {
      "index": 7,
      "text": "B= Piero] SMA AeA! SoH! Ql Ats|4I SEATS la=S? Afs|Aq SFAPEtO] Ol Al G= AAS! ol SOS! SAS] SF BE OPO] BAY Wa] AYO] ZOHO! Old I} D SOHO! Sl Oj] CHSt SOHC HIBOHelS| SATH SAO] ->ARCH SL ===PAGE_BREAK=== ZOHO! ARBSALE NOE BO AS RE MASSE! SOHCIAFS SAIS (2007.42 a2) Sols OlF= an BIEHG | BESHOHE Abs _ . o 5 @ Ae @! ol ol fmt ses WS O- HA A YAS =clet Ewa] 72 = AIOHO! rY AHStPt SAO} AS -7ra SAAS SHEA Ale Fos a2gas WSS Ae] S2| Aor 2 ee Api -SURIZIAy MBIA ASH SOAS -SonOks -ZAAIZY ZIOH ===PAGE_BREAK=== ZOHO1 ARIAT NOS BO AE RE MASSE! Sore! ABSA oS ASS  era he —_ - ol -F-2} 1417 he SHonelS SStot OF SLO] HHA AFOFAL aAlvsor sae les AStAect&S SOneloAl Sclst Sco} CHPOK= SBP2sS SeILict. Bap | SHO SCA OE 2rSArHOl OHS SILIC. BA: = ll aslals| ===PAGE_BREAK=== ZOHO! ARATE MOIS BO AE RE ASS! Sore! ABSA oS BSS BSSt MOMS AAO OSt Ap! Salo QISt ANA O18 BBA Me SOMA WH seo trot SEOlLt Saxo] Hetst Ara ze Sal9| LHSO!] SOHO Chet HHA ASS Sesot OlF ROl SOMPIAA| AS|AISOiLt sclot HSS LEE 3S AMHIA SI ASS ASOeE SSS BEILIC. Ol= S104] Qist APBOI OHS SLICt. BA: = 7llasl2s| ===PAGE_BREAK=== boo BISt MOBS SOHO] SSSt 1S Bt SHAS SAlS Alaa ASI ALF ol oH elo] sto] BIR Wo] ABS ARs BP's apy] et eyoe ay 7”? 66 LL oT = -19}-"
    },
    {
      "index": 8,
      "text": "Soot HAMS AHO Qlet AS 66 Qe HO)'=} Ye oqo] Foq7t AE AY} SSS] BL PE] Bod + YES 99 Ato Ol] AH ZtoHo] OA WM AG SA Sg West TO} A]AY- Aly] - E-. AWA = OlAzl. eA Aq] Bt aT} 5} AA|z Oto}c} -23}- SSct HOS Sa He AasolAl BQ/ @ ao Bel Ale, A AHHHAl DAAlA AIA Al 7H AJSSHS] SAIL HA, APAS, 37 Alt _ —_J SOl7 I AAS AA LOSSY - SE HO ZYOIAy A Hs ===PAGE_BREAK=== Soot HOAS AHO Qlet AS Soot HMOMNSO= S29 SStt SS BO AAS On SOT SA HE SSet HAS Act O}SO!| OFSCHA, L|E{0|| SICH SAW] ax ALZHE AIAISIC] BIO] PESOS Bt EL |E{01] StH SAI] AAI OJAAS Oil MIStOll VIS A SAjztzs TOSSA HACC oI EA BIOS Ae, ASAZS OA ASO] Zee AFH AS Jt HiIS-0] 127} PHSol me St ===PAGE_BREAK=== Soot HOAS AHO Qlet AS BIS MOMSOS BOHN] SSSt StS AO} foo > > Ls AHA [i] HE BESt MOPS Su 2S AAS ONS! DAT QNS85 BE AASOKS! SEA SA&, Sc lHlOle, =LO|AZ HlOlS SPI (sta rttss kes Ala -SHl7t 22 BAe! dQ AMARA Sis Oll 2Fot= QMABA SSA oSoe AAS?! DEA AASOHS! 2A SNS SSS let Higtst BS ehit OKI Slet BS BASS |7/02 Se7|2al 22 ===PAGE_BREAK=== Sone! ASA Bold! 0h Ale! SS > RSUG ASMA Sl SsSscnel Aas FASS IA] -SSCEM| 7401] (HE ASIA AH aan Sore! HASSHAIAl - - a — tH X{2A0 AZ SHHA see CAS AEC! AjH|AS AMSHS Sst SAA HBot= SAAT Sear LL otk on Tse a assz atone! SScorel! Quix"
    },
    {
      "index": 9,
      "text": "SHzy|2 BSTC! CH APIS Als, AY S AST Ht PHS AISI Bh soba s AIG SH Sh ATA! Ast AI ApeIzs —y_| eS SHEE. A> A| el WHA ===PAGE_BREAK=== SOW?! AAS Bold! gC Ale SS > RSUG Soe! ASSSHMlAl TEAlHel Ae AIS SIBSL= SOK! As S AP AOl AF AlBl OF BAI OlAt BSA OlSFO| SHOHO! Torr — C=. G é fi AI AERA} = ASS uz o ols A121 MB CHS | | 40159 Ale! > aes aaa S38 FW! Sane Als Sole! AAW a Nao|> Ayo] a A A siazigqo: ) SAZ St0H0l DSA SA] 2OS Ole 2c} a : n iZ : Oe Ie _ ame _. SoS = BtOHO! Assy IS IS BASAL 2A MS A WISE SE ISTE ===PAGE_BREAK=== Ve -FOHMDSS St +7 °° 7] 919] Aps}24 7}2] ao] Awe, ZOHO] 31-2, e7] sta Zo] ehcp oASLICN"
    }
  ]
}